cdklabs/cdk_proserve_lib/__init__.py
cdklabs/cdk_proserve_lib/py.typed
cdklabs/cdk_proserve_lib/_jsii/__init__.py
cdklabs/cdk_proserve_lib/_jsii/cdk-proserve-lib@0.13.4.jsii.tgz
cdklabs/cdk_proserve_lib/aspects/__init__.py
cdklabs/cdk_proserve_lib/constructs/__init__.py
cdklabs/cdk_proserve_lib/patterns/__init__.py
cdklabs/cdk_proserve_lib/types/__init__.py
cdklabs_cdk_proserve_lib-0.13.4.dist-info/LICENSE
cdklabs_cdk_proserve_lib-0.13.4.dist-info/METADATA
cdklabs_cdk_proserve_lib-0.13.4.dist-info/NOTICE
cdklabs_cdk_proserve_lib-0.13.4.dist-info/WHEEL
cdklabs_cdk_proserve_lib-0.13.4.dist-info/top_level.txt
cdklabs_cdk_proserve_lib-0.13.4.dist-info/RECORD
